yassine_string_utils/__init__.py
yassine_string_utils/string_ops.py
yassine_string_utils-0.1.0.dist-info/METADATA
yassine_string_utils-0.1.0.dist-info/WHEEL
yassine_string_utils-0.1.0.dist-info/RECORD
